drf_simple_oauth2-1.0.5.dist-info/licenses/LICENSE
simple_oauth2/__init__.py
simple_oauth2/apps.py
simple_oauth2/enums.py
simple_oauth2/exceptions.py
simple_oauth2/models.py
simple_oauth2/serializers.py
simple_oauth2/settings.py
simple_oauth2/urls.py
simple_oauth2/utils.py
simple_oauth2/views.py
simple_oauth2/migrations/0001_initial.py
simple_oauth2/migrations/0002_alter_session_status.py
simple_oauth2/migrations/__init__.py
drf_simple_oauth2-1.0.5.dist-info/METADATA
drf_simple_oauth2-1.0.5.dist-info/WHEEL
drf_simple_oauth2-1.0.5.dist-info/top_level.txt
drf_simple_oauth2-1.0.5.dist-info/RECORD
