Metadata-Version: 2.4
Name: drf-simple-oauth2
Version: 1.0.5
Summary: Simple OAuth2 client package allowing to define OAuth2 / OpenID providers through settings.
Author-email: "Quentin Coumes (Codoc)" <quentin@codoc.co>
License-Expression: MIT
Project-URL: Homepage, https://github.com/Codoc-os/drf-simple-oauth2
Project-URL: Documentation, https://drf-simple-oauth2.readthedocs.io/en/latest/
Project-URL: Changelog, https://github.com/Codoc-os/drf-simple-oauth2/blob/main/CHANGELOG.md
Project-URL: Issues, https://github.com/Codoc-os/drf-simple-oauth2/issues
Keywords: django,simple_oauth2,oauth2,oauth,openid,authentication
Classifier: Development Status :: 5 - Production/Stable
Classifier: Framework :: Django
Classifier: Framework :: Django :: 4.2
Classifier: Framework :: Django :: 5
Classifier: Framework :: Django :: 6
Classifier: Intended Audience :: Developers
Classifier: Natural Language :: English
Classifier: Programming Language :: Python :: 3 :: Only
Classifier: Programming Language :: Python :: 3.10
Classifier: Programming Language :: Python :: 3.11
Classifier: Programming Language :: Python :: 3.12
Classifier: Programming Language :: Python :: 3.13
Classifier: Programming Language :: Python :: 3.14
Classifier: Topic :: Internet :: WWW/HTTP
Classifier: Topic :: Security :: Cryptography
Requires-Python: >=3.10
License-File: LICENSE
Requires-Dist: django<7.0.0,>=4.0.0
Requires-Dist: djangorestframework<4.0.0,>=3.0.0
Requires-Dist: djangorestframework-simplejwt<6.0.0,>=5.0.0
Requires-Dist: pyjwt<3.0.0,>=2.6.0
Requires-Dist: requests<3.0.0,>=2.32.0
Dynamic: license-file
